{
  "internal_code": "A0001",
  "display_name": "塗布装置",
  "units": [
    {
      "label": "供給部",
      "sort_order": 0,
      "modules": [
        {
          "label": "M000供給ﾏｶﾞｼﾞﾝ_ﾏｶﾞｼﾞﾝｾｯﾄ位置",
          "sort_order": 0
        },
        {
          "label": "M001供給ﾏｶﾞｼﾞﾝ_SUS板取出位置",
          "sort_order": 1
        },
        {
          "label": "M002供給SUS板_取",
          "sort_order": 2
        },
        {
          "label": "M003供給SUS板_置",
          "sort_order": 3
        },
        {
          "label": "M004供給SUS板_検査",
          "sort_order": 4
        },
        {
          "label": "M005供給搬送1_取",
          "sort_order": 5
        },
        {
          "label": "M006供給搬送1_置",
          "sort_order": 6
        },
        {
          "label": "M007供給搬送1_戻",
          "sort_order": 7
        }
      ]
    },
    {
      "label": "塗布1部",
      "sort_order": 1,
      "modules": [
        {
          "label": "M016塗布1搬送1_取1(供給搬送2)",
          "sort_order": 16
        },
        {
          "label": "M017塗布1搬送1_取2(塗布TB)",
          "sort_order": 17
        },
        {
          "label": "M018塗布1搬送2_取3(ﾚﾍﾞﾘﾝｸﾞ)",
          "sort_order": 18
        },
        {
          "label": "M019塗布1搬送2_取4(外観検査)",
          "sort_order": 19
        },
        {
          "label": "M020塗布1搬送2_取5(寸法検査)",
          "sort_order": 20
        },
        {
          "label": "M021塗布1搬送3_取6(乾燥前)",
          "sort_order": 21
        },
        {
          "label": "M022塗布1搬送3_取7(予約)",
          "sort_order": 22
        },
        {
          "label": "M023塗布1搬送3_取8(乾燥)",
          "sort_order": 23
        },
        {
          "label": "M024塗布1搬送3_取9(冷却)",
          "sort_order": 24
        },
        {
          "label": "M025塗布1搬送3_取10(塗布1回転1)",
          "sort_order": 25
        },
        {
          "label": "M026塗布1搬送1_置1(塗布TB)",
          "sort_order": 26
        },
        {
          "label": "M027塗布1搬送2_置2(ﾚﾍﾞﾘﾝｸﾞ)",
          "sort_order": 27
        },
        {
          "label": "M028塗布1搬送2_置3(外観検査)",
          "sort_order": 28
        },
        {
          "label": "M029塗布1搬送2_置4(寸法検査)",
          "sort_order": 29
        },
        {
          "label": "M030塗布1搬送3_置5(NG排出)",
          "sort_order": 30
        },
        {
          "label": "M031塗布1搬送3_置6(乾燥前)",
          "sort_order": 31
        },
        {
          "label": "M032塗布1搬送3_置7(予約)",
          "sort_order": 32
        },
        {
          "label": "M033塗布1搬送3_置8(乾燥)",
          "sort_order": 33
        },
        {
          "label": "M034塗布1搬送3_置9(冷却)",
          "sort_order": 34
        },
        {
          "label": "M035塗布1搬送3_置10(塗布1回転1)",
          "sort_order": 35
        },
        {
          "label": "M036塗布1搬送3_置11(塗布1回転2)",
          "sort_order": 36
        },
        {
          "label": "M037塗布1_工程1.ｾｯﾄ位置",
          "sort_order": 37
        },
        {
          "label": "M038塗布1_工程2.ﾌﾞﾛｰ",
          "sort_order": 38
        },
        {
          "label": "M039塗布1_工程3.AL計測",
          "sort_order": 39
        },
        {
          "label": "M040塗布1_工程4.高さ計測",
          "sort_order": 40
        },
        {
          "label": "M041塗布1_工程5.塗布",
          "sort_order": 41
        },
        {
          "label": "M042塗布1_塗布清掃1.ｼｰﾄ",
          "sort_order": 42
        },
        {
          "label": "M043塗布1_塗布清掃2.ﾛｰﾙ",
          "sort_order": 43
        },
        {
          "label": "M044塗布1_外観検査",
          "sort_order": 44
        },
        {
          "label": "M045塗布1_寸法検査",
          "sort_order": 45
        }
      ]
    },
    {
      "label": "塗布2部",
      "sort_order": 2,
      "modules": [
        {
          "label": "M048塗布2搬送1_取1(塗布1回転2)",
          "sort_order": 48
        },
        {
          "label": "M049塗布2搬送1_取2(塗布TB)",
          "sort_order": 49
        },
        {
          "label": "M050塗布2搬送2_取3(ﾚﾍﾞﾘﾝｸﾞ)",
          "sort_order": 50
        },
        {
          "label": "M051塗布2搬送2_取4(外観検査)",
          "sort_order": 51
        },
        {
          "label": "M052塗布2搬送2_取5(寸法検査)",
          "sort_order": 52
        },
        {
          "label": "M053塗布2搬送3_取6(塗布2回転1)",
          "sort_order": 53
        },
        {
          "label": "M054塗布2搬送3_取7(塗布2回転2)",
          "sort_order": 54
        },
        {
          "label": "M055塗布2搬送3_取8(乾燥)",
          "sort_order": 55
        },
        {
          "label": "M056塗布2搬送3_取9(冷却)",
          "sort_order": 56
        },
        {
          "label": "M057塗布2搬送3_取10(予約)",
          "sort_order": 57
        },
        {
          "label": "M058塗布2搬送1_置1(塗布TB)",
          "sort_order": 58
        },
        {
          "label": "M059塗布2搬送1_置2(ﾚﾍﾞﾘﾝｸﾞ)",
          "sort_order": 59
        },
        {
          "label": "M060塗布2搬送2_置3(外観検査)",
          "sort_order": 60
        },
        {
          "label": "M061塗布2搬送2_置4(寸法検査)",
          "sort_order": 61
        },
        {
          "label": "M062塗布2搬送2_置5(NG排出)",
          "sort_order": 62
        },
        {
          "label": "M063塗布2搬送2_置6(塗布2回転1)",
          "sort_order": 63
        },
        {
          "label": "M064塗布2搬送3_置7(塗布2回転2)",
          "sort_order": 64
        },
        {
          "label": "M065塗布2搬送3_置8(乾燥)",
          "sort_order": 65
        },
        {
          "label": "M066塗布2搬送3_置9(冷却)",
          "sort_order": 66
        },
        {
          "label": "M067塗布2搬送3_置10(塗布2仮置)",
          "sort_order": 67
        },
        {
          "label": "M068塗布2_置11(予約)",
          "sort_order": 68
        },
        {
          "label": "M069塗布2_工程1.ｾｯﾄ位置",
          "sort_order": 69
        },
        {
          "label": "M070塗布2_工程2.ﾌﾞﾛｰ",
          "sort_order": 70
        },
        {
          "label": "M071塗布2_工程3.AL計測",
          "sort_order": 71
        },
        {
          "label": "M072塗布2_工程4.高さ計測",
          "sort_order": 72
        },
        {
          "label": "M073塗布2_工程5.塗布",
          "sort_order": 73
        },
        {
          "label": "M074塗布2_塗布清掃1.ｼｰﾄ",
          "sort_order": 74
        },
        {
          "label": "M075塗布2_塗布清掃2.ﾛｰﾙ",
          "sort_order": 75
        },
        {
          "label": "M076塗布2_外観検査",
          "sort_order": 76
        },
        {
          "label": "M077塗布2_寸法検査",
          "sort_order": 77
        }
      ]
    },
    {
      "label": "塗布3部",
      "sort_order": 3,
      "modules": [
        {
          "label": "M080塗布3搬送1_取1(塗布2仮置)",
          "sort_order": 80
        },
        {
          "label": "M081塗布3搬送1_取2(塗布TB)",
          "sort_order": 81
        },
        {
          "label": "M082塗布3搬送1_取3(ﾚﾍﾞﾘﾝｸﾞ)",
          "sort_order": 82
        },
        {
          "label": "M083塗布3搬送2_取4(外観検査)",
          "sort_order": 83
        },
        {
          "label": "M084塗布3搬送2_取5(寸法検査)",
          "sort_order": 84
        },
        {
          "label": "M085塗布3搬送3_取6(乾燥前)",
          "sort_order": 85
        },
        {
          "label": "M086塗布3搬送3_取7(予約)",
          "sort_order": 86
        },
        {
          "label": "M087塗布3搬送3_取8(乾燥)",
          "sort_order": 87
        },
        {
          "label": "M088塗布3搬送3_取9(冷却)",
          "sort_order": 88
        },
        {
          "label": "M089塗布3搬送3_取10(予約)",
          "sort_order": 89
        },
        {
          "label": "M090塗布3搬送1_置1(塗布TB)",
          "sort_order": 90
        },
        {
          "label": "M091塗布3搬送1_置2(ﾚﾍﾞﾘﾝｸﾞ)",
          "sort_order": 91
        },
        {
          "label": "M092塗布3搬送2_置3(外観検査)",
          "sort_order": 92
        },
        {
          "label": "M093塗布3搬送2_置4(寸法検査)",
          "sort_order": 93
        },
        {
          "label": "M094塗布3搬送2_置5(NG排出)",
          "sort_order": 94
        },
        {
          "label": "M095塗布3搬送2_置6(乾燥前)",
          "sort_order": 95
        },
        {
          "label": "M096塗布3搬送3_置7(予約)",
          "sort_order": 96
        },
        {
          "label": "M097塗布3搬送3_置8(乾燥)",
          "sort_order": 97
        },
        {
          "label": "M098塗布3搬送3_置9(冷却)",
          "sort_order": 98
        },
        {
          "label": "M099塗布3搬送3_置10(排出搬送2)",
          "sort_order": 99
        },
        {
          "label": "M100塗布3搬送3_置11(予約)",
          "sort_order": 100
        },
        {
          "label": "M101塗布3_工程1.ｾｯﾄ位置",
          "sort_order": 101
        },
        {
          "label": "M102塗布3_工程2.ﾌﾞﾛｰ",
          "sort_order": 102
        },
        {
          "label": "M103塗布3_工程3.AL計測",
          "sort_order": 103
        },
        {
          "label": "M104塗布3_工程4.高さ計測",
          "sort_order": 104
        },
        {
          "label": "M105塗布3_工程5.塗布",
          "sort_order": 105
        },
        {
          "label": "M106塗布3_塗布清掃1.ｼｰﾄ",
          "sort_order": 106
        },
        {
          "label": "M107塗布3_塗布清掃2.ﾛｰﾙ",
          "sort_order": 107
        },
        {
          "label": "M108塗布3_外観検査",
          "sort_order": 108
        },
        {
          "label": "M109塗布3_寸法検査",
          "sort_order": 109
        }
      ]
    },
    {
      "label": "収納部",
      "sort_order": 4,
      "modules": [
        {
          "label": "M112収納ﾏｶﾞｼﾞﾝ搬送_ﾏｶﾞｼﾞﾝｾｯﾄ位置",
          "sort_order": 112
        },
        {
          "label": "M113収納ﾏｶﾞｼﾞﾝ搬送_SUS板取出位置",
          "sort_order": 113
        },
        {
          "label": "M114収納SUS板搬送_取",
          "sort_order": 114
        },
        {
          "label": "M115収納SUS板搬送_置",
          "sort_order": 115
        },
        {
          "label": "M118収納搬送1_取",
          "sort_order": 118
        },
        {
          "label": "M119収納搬送1_置",
          "sort_order": 119
        }
      ]
    }
  ],
  "flows": [
    {
      "unit_label": "供給部",
      "module_label": "M000供給ﾏｶﾞｼﾞﾝ_ﾏｶﾞｼﾞﾝｾｯﾄ位置",
      "title": "M000供給ﾏｶﾞｼﾞﾝ_ﾏｶﾞｼﾞﾝｾｯﾄ位置",
      "payload": {
        "version": 1,
        "schema": "table-10col-v2",
        "title": "M000供給ﾏｶﾞｼﾞﾝ_ﾏｶﾞｼﾞﾝｾｯﾄ位置",
        "layout": {
          "width": 160,
          "heightMin": 60,
          "gapV": 30,
          "gapH": 100,
          "baseLeft": 40,
          "baseTop": 40
        },
        "table": [
          [
            "1",
            "端子",
            "",
            "2",
            "",
            "1",
            "0",
            "MR41000",
            "供給ﾏｶﾞｼﾞﾝ_ﾏｶﾞｼﾞﾝｾｯﾄ位置_開始",
            ""
          ],
          [
            "2",
            "処理",
            "",
            "3",
            "",
            "2",
            "0",
            "MR41100",
            "RC008_供給ﾏｶﾞｼﾞﾝz",
            "P01_下降"
          ],
          [
            "3",
            "処理",
            "",
            "4",
            "",
            "3",
            "0",
            "MR41102",
            "RC001_供給ﾏｶﾞｼﾞﾝy",
            "P01_ﾏｶﾞｼﾞﾝｾｯﾄ"
          ],
          [
            "4",
            "端子",
            "",
            "",
            "",
            "4",
            "0",
            "MR41001",
            "供給ﾏｶﾞｼﾞﾝ_ﾏｶﾞｼﾞﾝｾｯﾄ位置_終了",
            ""
          ]
        ],
        "createdAt": "2026-06-26T12:07:44.000Z"
      }
    },
    {
      "unit_label": "供給部",
      "module_label": "M001供給ﾏｶﾞｼﾞﾝ_SUS板取出位置",
      "title": "M001供給ﾏｶﾞｼﾞﾝ_SUS板取出位置",
      "payload": {
        "version": 1,
        "schema": "table-10col-v2",
        "title": "M001供給ﾏｶﾞｼﾞﾝ_SUS板取出位置",
        "layout": {
          "width": 160,
          "heightMin": 60,
          "gapV": 30,
          "gapH": 100,
          "baseLeft": 40,
          "baseTop": 40
        },
        "table": [
          [
            "1",
            "端子",
            "",
            "2",
            "",
            "1",
            "0",
            "MR41500",
            "供給ﾏｶﾞｼﾞﾝ_SUS板取出位置_開始",
            ""
          ],
          [
            "2",
            "処理",
            "",
            "3",
            "",
            "2",
            "0",
            "MR41600",
            "RC008_供給ﾏｶﾞｼﾞﾝz",
            "P01_下降"
          ],
          [
            "3",
            "処理",
            "",
            "4",
            "",
            "3",
            "0",
            "MR41602",
            "RC001_供給ﾏｶﾞｼﾞﾝy",
            "P02_SUS取出"
          ],
          [
            "4",
            "端子",
            "",
            "",
            "",
            "4",
            "",
            "MR41501",
            "供給ﾏｶﾞｼﾞﾝ_SUS板取出位置_終了",
            ""
          ]
        ],
        "createdAt": "2026-06-26T12:07:44.000Z"
      }
    },
    {
      "unit_label": "供給部",
      "module_label": "M002供給SUS板_取",
      "title": "M002供給SUS板_取",
      "payload": {
        "version": 1,
        "schema": "table-10col-v2",
        "title": "M002供給SUS板_取",
        "layout": {
          "width": 160,
          "heightMin": 60,
          "gapV": 30,
          "gapH": 100,
          "baseLeft": 40,
          "baseTop": 40
        },
        "table": [
          [
            "1",
            "端子",
            "",
            "2",
            "",
            "1",
            "0",
            "MR42000",
            "供給_SUS板搬送_取_開始",
            ""
          ],
          [
            "2",
            "処理",
            "",
            "3,4,5",
            "",
            "2",
            "0",
            "MR42100",
            "RC008_供給ﾏｶﾞｼﾞﾝz",
            "P03_SUS取出下"
          ],
          [
            "3",
            "処理",
            "",
            "6",
            "",
            "3",
            "1",
            "MR42102",
            "供給SUSｽﾄｯﾊﾟｰ",
            "_出"
          ],
          [
            "4",
            "処理",
            "",
            "6",
            "",
            "4",
            "2",
            "MR42104",
            "供給SUS板引供給ｼｬｯﾀｰ",
            "_開"
          ],
          [
            "5",
            "処理",
            "",
            "6",
            "",
            "5",
            "3",
            "MR42106",
            "RC002_供給SUS板引y",
            "P02_SUS取出"
          ],
          ["6", "処理", "", "7", "", "6", "0", "MR42108", "SUS板取", "準備OK"],
          [
            "7",
            "処理",
            "",
            "8",
            "",
            "7",
            "0",
            "MR42200",
            "RC003_供給SUS板引x",
            "P02_SUS取出"
          ],
          [
            "8",
            "処理",
            "",
            "9",
            "",
            "8",
            "0",
            "MR42202",
            "RC008_供給ﾏｶﾞｼﾞﾝz",
            "P02_SUS取出上"
          ],
          [
            "9",
            "処理",
            "",
            "10",
            "",
            "9",
            "0",
            "MR42204",
            "供給SUS板引出ﾁｬｯｸ左右",
            "_閉"
          ],
          [
            "10",
            "処理",
            "",
            "11",
            "",
            "10",
            "0",
            "MR42206",
            "SUS板取完了",
            "_フラグシフト"
          ],
          [
            "11",
            "処理",
            "",
            "12,13",
            "",
            "11",
            "0",
            "MR42300",
            "RC003_供給SUS板引x",
            "P01_戻"
          ],
          [
            "12",
            "処理",
            "",
            "14",
            "",
            "12",
            "1",
            "MR42302",
            "供給SUSｽﾄｯﾊﾟｰ",
            "_戻"
          ],
          [
            "13",
            "処理",
            "",
            "14",
            "",
            "13",
            "2",
            "MR42304",
            "供給SUS板引供給ｼｬｯﾀｰ",
            "_閉"
          ],
          [
            "14",
            "端子",
            "",
            "",
            "",
            "14",
            "0",
            "MR42001",
            "供給_SUS板搬送_取_終了",
            ""
          ]
        ],
        "createdAt": "2026-06-26T12:07:44.000Z"
      }
    },
    {
      "unit_label": "供給部",
      "module_label": "M003供給SUS板_置",
      "title": "M003供給SUS板_置",
      "payload": {
        "version": 1,
        "schema": "table-10col-v2",
        "title": "M003供給SUS板_置",
        "layout": {
          "width": 160,
          "heightMin": 60,
          "gapV": 30,
          "gapH": 100,
          "baseLeft": 40,
          "baseTop": 40
        },
        "table": [
          [
            "1",
            "端子",
            "",
            "2",
            "",
            "1",
            "0",
            "MR42500",
            "供給_SUS板搬送_置_開始",
            ""
          ],
          [
            "2",
            "処理",
            "",
            "3,4,5",
            "",
            "2",
            "0",
            "MR42600",
            "RC008_供給ﾏｶﾞｼﾞﾝz",
            "P02_SUS取出上"
          ],
          [
            "3",
            "処理",
            "",
            "6",
            "",
            "3",
            "1",
            "MR42602",
            "供給SUSｽﾄｯﾊﾟｰ",
            "_出"
          ],
          [
            "4",
            "処理",
            "",
            "6",
            "",
            "4",
            "2",
            "MR42604",
            "供給SUS板引供給ｼｬｯﾀｰ",
            "_開"
          ],
          [
            "5",
            "処理",
            "",
            "6",
            "",
            "5",
            "3",
            "MR42606",
            "RC002_供給SUS板引y",
            "P02_SUS取出"
          ],
          ["6", "処理", "", "7", "", "6", "0", "MR42608", "SUS板置", "準備OK"],
          [
            "7",
            "処理",
            "",
            "8",
            "",
            "7",
            "0",
            "MR42700",
            "RC003_供給SUS板引x",
            "P02_SUS取出"
          ],
          [
            "8",
            "処理",
            "",
            "9",
            "",
            "8",
            "0",
            "MR42702",
            "RC008_供給ﾏｶﾞｼﾞﾝz",
            "P03_SUS取出下"
          ],
          [
            "9",
            "処理",
            "",
            "10",
            "",
            "9",
            "0",
            "MR42704",
            "供給SUS板引出ﾁｬｯｸ左右",
            "_開"
          ],
          [
            "10",
            "処理",
            "",
            "11",
            "",
            "10",
            "0",
            "MR42706",
            "SUS板取完了",
            "_フラグシフト"
          ],
          [
            "11",
            "処理",
            "",
            "12,13",
            "",
            "11",
            "0",
            "MR42800",
            "RC003_供給SUS板引x",
            "P01_戻"
          ],
          [
            "12",
            "処理",
            "",
            "14",
            "",
            "12",
            "1",
            "MR42802",
            "供給SUSｽﾄｯﾊﾟｰ",
            "_戻"
          ],
          [
            "13",
            "処理",
            "",
            "14",
            "",
            "13",
            "2",
            "MR42804",
            "供給SUS板引供給ｼｬｯﾀｰ",
            "_閉"
          ],
          [
            "14",
            "端子",
            "",
            "",
            "",
            "14",
            "0",
            "MR42501",
            "供給_SUS板搬送_置_終了",
            ""
          ]
        ],
        "createdAt": "2026-06-26T12:07:44.000Z"
      }
    },
    {
      "unit_label": "供給部",
      "module_label": "M004供給SUS板_検査",
      "title": "M004供給SUS板_検査",
      "payload": {
        "version": 1,
        "schema": "table-10col-v2",
        "title": "M004供給SUS板_検査",
        "layout": {
          "width": 160,
          "heightMin": 60,
          "gapV": 30,
          "gapH": 100,
          "baseLeft": 40,
          "baseTop": 40
        },
        "table": [
          [
            "1",
            "端子",
            "",
            "2",
            "",
            "1",
            "0",
            "MR43000",
            "供給_SUS板搬送_検査_開始",
            ""
          ],
          [
            "2",
            "処理",
            "",
            "3",
            "",
            "2",
            "0",
            "MR43100",
            "RC002_供給SUS板引y",
            "P03_検査位置"
          ],
          ["3", "処理", "", "4", "", "3", "0", "MR43200", "SUS検査", "計測"],
          [
            "4",
            "判断",
            "",
            "6",
            "5",
            "4",
            "0",
            "MR43204",
            "SUS検査",
            "結果確認"
          ],
          [
            "5",
            "処理",
            "",
            "6",
            "",
            "5",
            "1",
            "MR43208",
            "ALXXX",
            "画像検査異常"
          ],
          [
            "6",
            "処理",
            "",
            "7",
            "",
            "6",
            "0",
            "MR43210",
            "SUS検査",
            "_フラグシフト"
          ],
          [
            "7",
            "端子",
            "",
            "",
            "",
            "7",
            "0",
            "MR43001",
            "供給_SUS板搬送_検査_終了",
            ""
          ]
        ],
        "createdAt": "2026-06-26T12:07:44.000Z"
      }
    },
    {
      "unit_label": "供給部",
      "module_label": "M005供給搬送1_取",
      "title": "M005供給搬送1_取",
      "payload": {
        "version": 1,
        "schema": "table-10col-v2",
        "title": "M005供給搬送1_取",
        "layout": {
          "width": 160,
          "heightMin": 60,
          "gapV": 30,
          "gapH": 100,
          "baseLeft": 40,
          "baseTop": 40
        },
        "table": [
          [
            "1",
            "端子",
            "",
            "2,3",
            "",
            "1",
            "0",
            "MR43500",
            "供給_個片搬送1(取出)_取_開始",
            ""
          ],
          [
            "2",
            "処理",
            "",
            "4",
            "",
            "2",
            "1",
            "MR43600",
            "RC002_供給SUS板引y",
            "P05_受渡"
          ],
          [
            "3",
            "処理",
            "",
            "4",
            "",
            "3",
            "2",
            "MR43602",
            "RC003_供給SUS板引x",
            "P05_受渡"
          ],
          ["4", "処理", "", "5", "", "4", "0", "MR43604", "個片取", "準備OK"],
          [
            "5",
            "処理",
            "",
            "6",
            "",
            "5",
            "0",
            "MR43701",
            "RC004_供給個片移載z",
            "P02_下降(SUS板)"
          ],
          [
            "6",
            "処理",
            "",
            "7",
            "",
            "6",
            "0",
            "MR43703",
            "RC005_供給個片移載c",
            "P02_閉-1mm"
          ],
          [
            "7",
            "処理",
            "",
            "8",
            "",
            "7",
            "0",
            "MR43705",
            "RC005_供給個片移載c",
            "P03_閉"
          ],
          [
            "8",
            "処理",
            "",
            "9",
            "",
            "8",
            "0",
            "MR43707",
            "個片取出",
            "_フラグシフト"
          ],
          [
            "9",
            "端子",
            "",
            "10",
            "",
            "9",
            "0",
            "MR43709",
            "RC004_供給個片移載z",
            "P01_上昇"
          ],
          [
            "10",
            "端子",
            "",
            "",
            "",
            "10",
            "0",
            "MR43501",
            "供給_個片搬送1(取出)_取_終了",
            ""
          ]
        ],
        "createdAt": "2026-06-26T12:07:44.000Z"
      }
    },
    {
      "unit_label": "供給部",
      "module_label": "M006供給搬送1_置",
      "title": "M006供給搬送1_置",
      "payload": {
        "version": 1,
        "schema": "table-10col-v2",
        "title": "M006供給搬送1_置",
        "layout": {
          "width": 160,
          "heightMin": 60,
          "gapV": 30,
          "gapH": 100,
          "baseLeft": 40,
          "baseTop": 40
        },
        "table": [
          [
            "1",
            "端子",
            "",
            "2,3,4",
            "",
            "1",
            "0",
            "MR44000",
            "供給搬送1_置_x001F__開始",
            ""
          ],
          [
            "2",
            "処理",
            "",
            "5",
            "",
            "2",
            "1",
            "MR44100",
            "RC002_供給SUS板引y",
            "P04_退避"
          ],
          [
            "3",
            "処理",
            "",
            "5",
            "",
            "3",
            "2",
            "MR44102",
            "RC006_供給個片y",
            "P01_受取(手前)"
          ],
          [
            "4",
            "処理",
            "",
            "5",
            "",
            "4",
            "3",
            "MR44104",
            "RC007_供給個片r",
            "P01_受取"
          ],
          ["5", "処理", "", "6", "", "5", "0", "MR44106", "個片置", "準備OK"],
          [
            "6",
            "処理",
            "",
            "7",
            "",
            "6",
            "0",
            "MR44200",
            "RC004_供給個片移載z",
            "P03_下降(供給個片)"
          ],
          [
            "7",
            "処理",
            "",
            "8",
            "",
            "7",
            "0",
            "MR44202",
            "供給搬送2真空",
            "_吸着"
          ],
          [
            "8",
            "処理",
            "",
            "9",
            "",
            "8",
            "0",
            "MR44204",
            "RC005_供給個片移載c",
            "P01_開"
          ],
          [
            "9",
            "処理",
            "",
            "10",
            "",
            "9",
            "0",
            "MR44206",
            "個片取出",
            "_ﾌﾗｸﾞｼﾌﾄ"
          ],
          [
            "10",
            "判断",
            "",
            "12",
            "11",
            "10",
            "0",
            "MR44300",
            "供給搬送2真空",
            "_吸着確認"
          ],
          [
            "11",
            "処理",
            "",
            "12",
            "",
            "11",
            "1",
            "MR44303",
            "ALXXX",
            "吸着ミス"
          ],
          [
            "12",
            "処理",
            "",
            "",
            "",
            "12",
            "",
            "MR44304",
            "RC004_供給個片移載z",
            "P01_上昇"
          ],
          [
            "13",
            "端子",
            "",
            "",
            "",
            "13",
            "",
            "MR44001",
            "供給搬送1_置_x001F__終了",
            ""
          ]
        ],
        "createdAt": "2026-06-26T12:07:44.000Z"
      }
    },
    {
      "unit_label": "供給部",
      "module_label": "M007供給搬送1_戻",
      "title": "M007供給搬送1_戻",
      "payload": {
        "version": 1,
        "schema": "table-10col-v2",
        "title": "M007供給搬送1_戻",
        "layout": {
          "width": 160,
          "heightMin": 60,
          "gapV": 30,
          "gapH": 100,
          "baseLeft": 40,
          "baseTop": 40
        },
        "table": [
          ["10", "端子", "", "20", "", "1", "0", "開始", "", ""],
          ["20", "処理", "", "30", "", "2", "0", "動作007", "", ""],
          ["30", "端子", "", "", "", "3", "0", "終了", "", ""]
        ],
        "createdAt": "2026-06-26T12:07:44.000Z"
      }
    },
    {
      "unit_label": "塗布1部",
      "module_label": "M018塗布1搬送2_取3(ﾚﾍﾞﾘﾝｸﾞ)",
      "title": "M018塗布1搬送2_取3(ﾚﾍﾞﾘﾝｸﾞ)",
      "payload": {
        "version": 1,
        "schema": "table-10col-v2",
        "title": "M018塗布1搬送2_取3(ﾚﾍﾞﾘﾝｸﾞ)",
        "layout": {
          "width": 160,
          "heightMin": 60,
          "gapV": 30,
          "gapH": 100,
          "baseLeft": 40,
          "baseTop": 40
        },
        "table": [
          [
            "1",
            "端子",
            "",
            "2,4",
            "",
            "1",
            "0",
            "MR230000",
            "塗布1搬送1_取1(供給搬送2)_開始",
            ""
          ],
          [
            "2",
            "処理",
            "",
            "3",
            "",
            "2",
            "1",
            "MR230100",
            "RC013_塗布1搬送1RB.x",
            "P03_供給2TB退避"
          ],
          [
            "3",
            "処理",
            "",
            "6",
            "",
            "3",
            "1",
            "MR230102",
            "RC016_塗布1搬送1RB.r",
            "P01_縦"
          ],
          [
            "4",
            "処理",
            "",
            "5",
            "",
            "4",
            "2",
            "MR230104",
            "RC006_供給搬送2TB.y",
            "P02_受渡(奥)"
          ],
          [
            "5",
            "処理",
            "",
            "6",
            "",
            "5",
            "2",
            "MR230106",
            "RC007_供給搬送2TB.r",
            "P02_受渡"
          ],
          ["6", "処理", "", "7", "", "6", "", "MR230108", "個片取出", "準備OK"],
          [
            "7",
            "処理",
            "",
            "8",
            "",
            "7",
            "",
            "MR230200",
            "RC014_塗布1搬送1RB.z",
            "P02_供給2TB"
          ],
          [
            "8",
            "処理",
            "",
            "9",
            "",
            "8",
            "",
            "MR230202",
            "RC013_塗布1搬送1RB.x",
            "P02_供給2TB"
          ],
          [
            "9",
            "処理",
            "",
            "10",
            "",
            "9",
            "",
            "MR230204",
            "RC015_塗布1搬送1RB.c",
            "P05_D.開-1mm"
          ],
          [
            "10",
            "処理",
            "",
            "11",
            "",
            "10",
            "",
            "MR230206",
            "RC015_塗布1搬送1RB.c",
            "P06_D.閉"
          ],
          [
            "11",
            "処理",
            "",
            "12",
            "",
            "11",
            "",
            "MR230208",
            "ｼﾌﾄ004_003←002",
            ""
          ],
          [
            "12",
            "処理",
            "",
            "13",
            "",
            "12",
            "",
            "MR230300",
            "供給搬送2真空",
            "_破壊"
          ],
          [
            "13",
            "処理",
            "",
            "14,15",
            "",
            "13",
            "",
            "MR230302",
            "RC014_塗布1搬送1RB.z",
            "P01_上昇"
          ],
          [
            "14",
            "処理",
            "",
            "16",
            "",
            "14",
            "1",
            "MR230304",
            "RC006_供給搬送2TB.y",
            "P01_受取(手前)"
          ],
          [
            "15",
            "処理",
            "",
            "16",
            "",
            "15",
            "2",
            "MR230306",
            "RC007_供給搬送2TB.r",
            "P01_受取"
          ],
          [
            "16",
            "端子",
            "",
            "",
            "",
            "16",
            "",
            "MR230001",
            "塗布1搬送1_取1(供給搬送2)_終了",
            ""
          ]
        ],
        "createdAt": "2026-06-26T12:07:44.000Z"
      }
    },
    {
      "unit_label": "塗布1部",
      "module_label": "M019塗布1搬送2_取4(外観検査)",
      "title": "M019塗布1搬送2_取4(外観検査)",
      "payload": {
        "version": 1,
        "schema": "table-10col-v2",
        "title": "M019塗布1搬送2_取4(外観検査)",
        "layout": {
          "width": 160,
          "heightMin": 60,
          "gapV": 30,
          "gapH": 100,
          "baseLeft": 40,
          "baseTop": 40
        },
        "table": [
          [
            "1",
            "端子",
            "",
            "2,3,4,5,6",
            "",
            "1",
            "",
            "MR230500",
            "開始_開始",
            ""
          ],
          [
            "2",
            "処理",
            "",
            "7",
            "",
            "2",
            "1",
            "MR230600",
            "RC013_塗布1搬送1RB.x",
            "P04_塗布TB"
          ],
          [
            "3",
            "処理",
            "",
            "7",
            "",
            "3",
            "2",
            "MR230602",
            "RC016_塗布1搬送1RB.r",
            "P01_縦"
          ],
          [
            "4",
            "処理",
            "",
            "7",
            "",
            "4",
            "3",
            "MR230604",
            "SMD01_塗布1TBy",
            "P01_受取"
          ],
          [
            "5",
            "処理",
            "",
            "7",
            "",
            "5",
            "4",
            "MR230606",
            "SMD02_塗布1TBx",
            "P01_受取"
          ],
          [
            "6",
            "処理",
            "",
            "7",
            "",
            "6",
            "5",
            "MR230608",
            "SMD03_塗布1TBr",
            "P01_受取"
          ],
          ["7", "処理", "", "8", "", "7", "", "MR230610", "個片取出", "準備OK"],
          [
            "8",
            "処理",
            "",
            "9",
            "",
            "8",
            "",
            "MR230700",
            "RC014_塗布1搬送1RB.z",
            "P04_塗布TB"
          ],
          [
            "9",
            "処理",
            "",
            "10",
            "",
            "9",
            "",
            "MR230702",
            "RC015_塗布1搬送1RB.c",
            "P05_D.開-1mm"
          ],
          [
            "10",
            "処理",
            "",
            "11",
            "",
            "10",
            "",
            "MR230704",
            "RC015_塗布1搬送1RB.c",
            "P06_D.閉"
          ],
          [
            "11",
            "処理",
            "",
            "12",
            "",
            "11",
            "",
            "MR230706",
            "ｼﾌﾄ006_003←004",
            ""
          ],
          [
            "12",
            "処理",
            "",
            "13",
            "",
            "12",
            "",
            "MR230800",
            "RC010_塗布1印刷TB.c",
            "P04_D.開"
          ],
          [
            "13",
            "処理",
            "",
            "14",
            "",
            "13",
            "",
            "MR230802",
            "RC014_塗布1搬送1RB.z",
            "P01_上昇"
          ],
          ["14", "端子", "", "", "", "14", "", "MR230501", "動作完了_終了", ""]
        ],
        "createdAt": "2026-06-26T12:07:44.000Z"
      }
    },
    {
      "unit_label": "塗布1部",
      "module_label": "M020塗布1搬送2_取5(寸法検査)",
      "title": "M020塗布1搬送2_取5(寸法検査)",
      "payload": {
        "version": 1,
        "schema": "table-10col-v2",
        "title": "M020塗布1搬送2_取5(寸法検査)",
        "layout": {
          "width": 160,
          "heightMin": 60,
          "gapV": 30,
          "gapH": 100,
          "baseLeft": 40,
          "baseTop": 40
        },
        "table": [
          [
            "1",
            "端子",
            "",
            "2",
            "",
            "1",
            "",
            "MR231000",
            "塗布1搬送2_取3(ﾚﾍﾞﾘﾝｸﾞ)_開始",
            ""
          ],
          [
            "2",
            "処理",
            "",
            "3",
            "",
            "2",
            "",
            "MR231100",
            "RC023_塗布1搬送2RB.x",
            "P02_ﾚﾍﾞﾘﾝｸﾞ(左)"
          ],
          [
            "3",
            "処理",
            "",
            "4",
            "",
            "3",
            "",
            "MR231102",
            "RC024_塗布1搬送2RB.z",
            "P02_ﾚﾍﾞﾘﾝｸﾞ(左)"
          ],
          [
            "4",
            "処理",
            "",
            "5",
            "",
            "4",
            "",
            "MR231104",
            "RC025_塗布1搬送2RB.c左",
            "P05_D.開-1mm"
          ],
          [
            "5",
            "処理",
            "",
            "6",
            "",
            "5",
            "",
            "MR231106",
            "RC025_塗布1搬送2RB.c左",
            "P06_D.閉"
          ],
          ["6", "判断", "", "9", "7", "6", "1", "EM60", "目標=", "1"],
          ["7", "判断", "", "10", "8", "7", "2", "EM60", "目標=", "2"],
          ["8", "処理", "", "11", "", "8", "3", "EM60", "目標=", "3"],
          [
            "9",
            "処理",
            "",
            "12",
            "",
            "9",
            "1",
            "MR231200",
            "ｼﾌﾄ010_008←005",
            "(EM60=1)"
          ],
          [
            "10",
            "処理",
            "",
            "12",
            "",
            "10",
            "2",
            "MR231202",
            "ｼﾌﾄ011_008←006",
            "(EM60=2)"
          ],
          [
            "11",
            "処理",
            "",
            "12",
            "",
            "11",
            "3",
            "MR231204",
            "ｼﾌﾄ012_008←007",
            "(EM60=3)"
          ],
          [
            "12",
            "処理",
            "",
            "13",
            "",
            "12",
            "",
            "MR231300",
            "RC024_塗布1搬送2RB.z",
            "P01_上昇"
          ],
          [
            "13",
            "端子",
            "",
            "",
            "",
            "13",
            "",
            "MR231001",
            "塗布1搬送2_取3(ﾚﾍﾞﾘﾝｸﾞ)_終了",
            ""
          ]
        ],
        "createdAt": "2026-06-26T12:07:44.000Z"
      }
    },
    {
      "unit_label": "塗布1部",
      "module_label": "M021塗布1搬送3_取6(乾燥前)",
      "title": "M021塗布1搬送3_取6(乾燥前)",
      "payload": {
        "version": 1,
        "schema": "table-10col-v2",
        "title": "M021塗布1搬送3_取6(乾燥前)",
        "layout": {
          "width": 160,
          "heightMin": 60,
          "gapV": 30,
          "gapH": 100,
          "baseLeft": 40,
          "baseTop": 40
        },
        "table": [
          [
            "1",
            "端子",
            "",
            "2,4",
            "",
            "1",
            "",
            "MR231500",
            "塗布1搬送2_取4(外観検査)_開始",
            ""
          ],
          [
            "2",
            "処理",
            "",
            "3",
            "",
            "2",
            "1",
            "MR231600",
            "RC023_塗布1搬送2RB.x",
            "P04_外観検査(右)"
          ],
          [
            "3",
            "処理",
            "",
            "5",
            "",
            "3",
            "1",
            "MR231602",
            "RC022_塗布1外観検査TB.x",
            "P01_戻"
          ],
          [
            "4",
            "処理",
            "",
            "5",
            "",
            "4",
            "2",
            "MR231604",
            "RC020_塗布1外観検査TB.y",
            "P01_戻"
          ],
          ["5", "処理", "", "6", "", "5", "", "MR231606", "個片取出", "準備OK"],
          [
            "6",
            "処理",
            "",
            "7",
            "",
            "6",
            "",
            "MR231700",
            "RC024_塗布1搬送2RB.z",
            "P04_外観検査(右)"
          ],
          [
            "7",
            "処理",
            "",
            "8",
            "",
            "7",
            "",
            "MR231702",
            "RC026_塗布1搬送2RB.c右",
            "P05_D.開-1mm"
          ],
          [
            "8",
            "処理",
            "",
            "9",
            "",
            "8",
            "",
            "MR231704",
            "RC026_塗布1搬送2RB.c右",
            "P06_D.閉"
          ],
          [
            "9",
            "処理",
            "",
            "10",
            "",
            "9",
            "",
            "MR231706",
            "ｼﾌﾄ014_009←010",
            ""
          ],
          [
            "10",
            "処理",
            "",
            "11",
            "",
            "10",
            "",
            "MR231800",
            "RC021_塗布1外観検査TB.c",
            "P01_W.開"
          ],
          [
            "11",
            "処理",
            "",
            "12",
            "",
            "11",
            "",
            "MR231802",
            "RC024_塗布1搬送2RB.z",
            "P01_上昇"
          ],
          [
            "12",
            "端子",
            "",
            "",
            "",
            "12",
            "",
            "MR231501",
            "塗布1搬送2_取4(外観検査)_終了",
            ""
          ]
        ],
        "createdAt": "2026-06-26T12:07:44.000Z"
      }
    },
    {
      "unit_label": "塗布1部",
      "module_label": "M022塗布1搬送3_取7(予約)",
      "title": "M022塗布1搬送3_取7(予約)",
      "payload": {
        "version": 1,
        "schema": "table-10col-v2",
        "title": "M022塗布1搬送3_取7(予約)",
        "layout": {
          "width": 160,
          "heightMin": 60,
          "gapV": 30,
          "gapH": 100,
          "baseLeft": 40,
          "baseTop": 40
        },
        "table": [
          [
            "1",
            "端子",
            "",
            "2",
            "",
            "1",
            "",
            "MR232000",
            "塗布1搬送2_取5(寸法検査)_開始",
            "0"
          ],
          [
            "2",
            "処理",
            "",
            "3",
            "",
            "2",
            "",
            "MR232100",
            "RC023_塗布1搬送2RB.x",
            "P05_寸法検査(右)"
          ],
          [
            "3",
            "処理",
            "",
            "4",
            "",
            "3",
            "",
            "MR232200",
            "RC024_塗布1搬送2RB.z",
            "P05_寸法検査(右)"
          ],
          [
            "4",
            "処理",
            "",
            "5",
            "",
            "4",
            "",
            "MR232202",
            "RC026_塗布1搬送2RB.c右",
            "P05_D.開-1mm"
          ],
          [
            "5",
            "処理",
            "",
            "6",
            "",
            "5",
            "",
            "MR232204",
            "RC026_塗布1搬送2RB.c右",
            "P06_D.閉"
          ],
          ["6", "処理", "", "7", "", "6", "", "MR232206", "ｼﾌﾄ015_009←011", ""],
          [
            "7",
            "処理",
            "",
            "8",
            "",
            "7",
            "",
            "MR232300",
            "RC019_塗布1寸法検査TB.c",
            "P01_W.開"
          ],
          [
            "8",
            "処理",
            "",
            "9",
            "",
            "8",
            "",
            "MR232302",
            "RC024_塗布1搬送2RB.z",
            "P01_上昇"
          ],
          [
            "9",
            "端子",
            "",
            "",
            "",
            "9",
            "",
            "MR232001",
            "塗布1搬送2_取5(寸法検査)_動作完了",
            ""
          ]
        ],
        "createdAt": "2026-06-26T12:07:44.000Z"
      }
    },
    {
      "unit_label": "塗布1部",
      "module_label": "M023塗布1搬送3_取8(乾燥)",
      "title": "M023塗布1搬送3_取8(乾燥)",
      "payload": {
        "version": 1,
        "schema": "table-10col-v2",
        "title": "M023塗布1搬送3_取8(乾燥)",
        "layout": {
          "width": 160,
          "heightMin": 60,
          "gapV": 30,
          "gapH": 100,
          "baseLeft": 40,
          "baseTop": 40
        },
        "table": [
          [
            "1",
            "端子",
            "",
            "2,3",
            "",
            "1",
            "",
            "MR232500",
            "塗布1搬送3_取6(乾燥前)_開始",
            ""
          ],
          [
            "2",
            "処理",
            "",
            "4",
            "",
            "2",
            "1",
            "MR232600",
            "RC029_塗布1搬送3RB.x",
            "P02_乾燥前"
          ],
          [
            "3",
            "処理",
            "",
            "4",
            "",
            "3",
            "2",
            "MR232602",
            "RC032_塗布1搬送3RB.r",
            "P02_横"
          ],
          ["4", "処理", "", "5", "", "4", "", "MR232604", "個片取出", "準備OK"],
          [
            "5",
            "処理",
            "",
            "6",
            "",
            "5",
            "",
            "MR232700",
            "RC030_塗布1搬送3RB.z",
            "P02_乾燥前"
          ],
          [
            "6",
            "処理",
            "",
            "7",
            "",
            "6",
            "",
            "MR232702",
            "RC031_塗布1搬送3RB.c",
            "P05_D.開-1mm"
          ],
          [
            "7",
            "処理",
            "",
            "8",
            "",
            "7",
            "",
            "MR232704",
            "RC031_塗布1搬送3RB.c",
            "P06_D.閉"
          ],
          ["8", "処理", "", "9", "", "8", "", "MR232706", "ｼﾌﾄ023_018←017", ""],
          [
            "9",
            "処理",
            "",
            "10",
            "",
            "9",
            "",
            "MR232800",
            "RC030_塗布1搬送3RB.z",
            "P01_上昇"
          ],
          [
            "10",
            "端子",
            "",
            "",
            "",
            "10",
            "",
            "MR232501",
            "塗布1搬送3_取6(乾燥前)_動作完了",
            ""
          ]
        ],
        "createdAt": "2026-06-26T12:07:44.000Z"
      }
    },
    {
      "unit_label": "塗布1部",
      "module_label": "M024塗布1搬送3_取9(冷却)",
      "title": "M024塗布1搬送3_取9(冷却)",
      "payload": {
        "version": 1,
        "schema": "table-10col-v2",
        "title": "M024塗布1搬送3_取9(冷却)",
        "layout": {
          "width": 160,
          "heightMin": 60,
          "gapV": 30,
          "gapH": 100,
          "baseLeft": 40,
          "baseTop": 40
        },
        "table": [["1", "端子", "", "", "", "", "", "", "", ""]],
        "createdAt": "2026-06-26T12:07:44.000Z"
      }
    },
    {
      "unit_label": "塗布1部",
      "module_label": "M025塗布1搬送3_取10(塗布1回転1)",
      "title": "M025塗布1搬送3_取10(塗布1回転1)",
      "payload": {
        "version": 1,
        "schema": "table-10col-v2",
        "title": "M025塗布1搬送3_取10(塗布1回転1)",
        "layout": {
          "width": 160,
          "heightMin": 60,
          "gapV": 30,
          "gapH": 100,
          "baseLeft": 40,
          "baseTop": 40
        },
        "table": [
          [
            "1",
            "端子",
            "",
            "2,3",
            "",
            "1",
            "",
            "MR233500",
            "塗布1搬送3_取8(乾燥)_開始",
            "0"
          ],
          [
            "2",
            "処理",
            "",
            "4",
            "",
            "2",
            "1",
            "MR233600",
            "RC029_塗布1搬送3RB.x",
            "P04_乾燥退避"
          ],
          [
            "3",
            "処理",
            "",
            "4",
            "",
            "3",
            "2",
            "MR233602",
            "RC032_塗布1搬送3RB.r",
            "P02_横"
          ],
          ["4", "処理", "", "5", "", "4", "", "MR233604", "個片取出", "準備OK"],
          [
            "5",
            "処理",
            "",
            "6",
            "",
            "5",
            "",
            "MR233700",
            "RC030_塗布1搬送3RB.z",
            "P04_乾燥退避"
          ],
          [
            "6",
            "処理",
            "",
            "7",
            "",
            "6",
            "",
            "MR233702",
            "RC029_塗布1搬送3RB.x",
            "P03_乾燥"
          ],
          [
            "7",
            "処理",
            "",
            "8",
            "",
            "7",
            "",
            "MR233704",
            "RC031_塗布1搬送3RB.c",
            "P05_D.開-1mm"
          ],
          [
            "8",
            "処理",
            "",
            "9",
            "",
            "8",
            "",
            "MR233706",
            "RC031_塗布1搬送3RB.c",
            "P06_D.閉"
          ],
          ["9", "判断", "", "17", "10", "9", "1", "EM80", "目標=", "1"],
          ["10", "判断", "", "18", "11", "10", "2", "EM80", "目標=", "2"],
          ["11", "判断", "", "19", "12", "11", "3", "EM80", "目標=", "3"],
          ["12", "判断", "", "20", "13", "12", "4", "EM80", "目標=", "4"],
          ["13", "判断", "", "21", "14", "13", "5", "EM80", "目標=", "5"],
          ["14", "判断", "", "22", "15", "14", "6", "EM80", "目標=", "6"],
          ["15", "判断", "", "23", "16", "15", "7", "EM80", "目標=", "7"],
          ["16", "処理", "", "24", "", "16", "8", "EM80", "目標=", "8"],
          [
            "17",
            "処理",
            "",
            "25",
            "",
            "17",
            "1",
            "MR233708",
            "ｼﾌﾄ032_018←019",
            "(EM80=1)"
          ],
          [
            "18",
            "処理",
            "",
            "25",
            "",
            "18",
            "2",
            "MR233710",
            "ｼﾌﾄ033_018←020",
            "(EM80=2)"
          ],
          [
            "19",
            "処理",
            "",
            "25",
            "",
            "19",
            "3",
            "MR233712",
            "ｼﾌﾄ034_018←021",
            "(EM80=3)"
          ],
          [
            "20",
            "処理",
            "",
            "25",
            "",
            "20",
            "4",
            "MR233714",
            "ｼﾌﾄ035_018←022",
            "(EM80=4)"
          ],
          [
            "21",
            "処理",
            "",
            "25",
            "",
            "21",
            "5",
            "MR233800",
            "ｼﾌﾄ036_018←023",
            "(EM80=5)"
          ],
          [
            "22",
            "処理",
            "",
            "25",
            "",
            "22",
            "6",
            "MR233802",
            "ｼﾌﾄ037_018←024",
            "(EM80=6)"
          ],
          [
            "23",
            "処理",
            "",
            "25",
            "",
            "23",
            "7",
            "MR233804",
            "ｼﾌﾄ038_018←025",
            "(EM80=7)"
          ],
          [
            "24",
            "処理",
            "",
            "25",
            "",
            "24",
            "8",
            "MR233806",
            "ｼﾌﾄ039_018←026",
            "(EM80=8)"
          ],
          [
            "25",
            "処理",
            "",
            "26",
            "",
            "25",
            "",
            "MR233808",
            "個片取出",
            "ｼﾌﾄOK"
          ],
          [
            "26",
            "処理",
            "",
            "27",
            "",
            "26",
            "",
            "MR233900",
            "RC024_塗布1搬送2RB.z",
            "P01_上昇"
          ],
          [
            "27",
            "端子",
            "",
            "",
            "",
            "27",
            "",
            "MR233501",
            "塗布1搬送3_取8(乾燥)_動作完了",
            ""
          ]
        ],
        "createdAt": "2026-06-26T12:07:44.000Z"
      }
    }
  ]
}
