{
  "version": 1,
  "schema": "table-10col-v1",
  "title": "サンプル: ATMで現金を下ろす",
  "layout": {
    "width": 160,
    "heightMin": 60,
    "gapV": 30,
    "gapH": 100,
    "baseLeft": 40,
    "baseTop": 40
  },
  "table": [
    [10, "端子", "20", "", 1, 0, "開始", "", "", ""],
    [20, "入出力", "30", "", 2, 0, "カードを挿入", "", "", ""],
    [30, "手動入力", "40", "", 3, 0, "暗証番号を入力", "", "", "青"],
    [40, "判断", "50", "60", 4, 0, "暗証番号は合う?", "", "", "黄"],
    [50, "処理", "70", "", 5, 0, "引き出し金額を入力", "", "", ""],
    [60, "端子", "", "", 5, 1, "終了（エラー）", "", "", "橙"],
    [70, "入出力", "80", "", 6, 0, "現金を受け取る", "", "", ""],
    [80, "処理", "90", "", 7, 0, "カードを取り出す", "", "", ""],
    [90, "端子", "", "", 8, 0, "終了", "", "", ""]
  ],
  "createdAt": "2026-06-06T00:00:00.000Z"
}
